LearningScrapyZhongwenban/README.md
LearningScrapyZhongwenban/__init__.py
LearningScrapyZhongwenban/__main__.py
LearningScrapyZhongwenban/file.epub
LearningScrapyZhongwenban/index.html
LearningScrapyZhongwenban/css/__init__.py
LearningScrapyZhongwenban/css/annotations.css
LearningScrapyZhongwenban/css/main.css
LearningScrapyZhongwenban/css/normalize.css
LearningScrapyZhongwenban/css/popup.css
LearningScrapyZhongwenban/font/__init__.py
LearningScrapyZhongwenban/font/fontello.eot
LearningScrapyZhongwenban/font/fontello.svg
LearningScrapyZhongwenban/font/fontello.ttf
LearningScrapyZhongwenban/font/fontello.woff
LearningScrapyZhongwenban/img/__init__.py
LearningScrapyZhongwenban/img/annotator-glyph-sprite.png
LearningScrapyZhongwenban/img/annotator-icon-sprite.png
LearningScrapyZhongwenban/img/apple-touch-icon.png
LearningScrapyZhongwenban/img/cancelfullscreen.png
LearningScrapyZhongwenban/img/close.png
LearningScrapyZhongwenban/img/fullscreen.png
LearningScrapyZhongwenban/img/loader.gif
LearningScrapyZhongwenban/img/menu-icon.png
LearningScrapyZhongwenban/img/save.png
LearningScrapyZhongwenban/img/saved.png
LearningScrapyZhongwenban/img/settings-s.png
LearningScrapyZhongwenban/img/settings.png
LearningScrapyZhongwenban/img/star.png
LearningScrapyZhongwenban/js/__init__.py
LearningScrapyZhongwenban/js/epub.js
LearningScrapyZhongwenban/js/epub.min.js
LearningScrapyZhongwenban/js/epub.min.map
LearningScrapyZhongwenban/js/hooks.min.js
LearningScrapyZhongwenban/js/hooks.min.map
LearningScrapyZhongwenban/js/reader.js
LearningScrapyZhongwenban/js/reader.js.map
LearningScrapyZhongwenban/js/reader.min.js
LearningScrapyZhongwenban/js/reader.min.map
LearningScrapyZhongwenban/js/hooks/__init__.py
LearningScrapyZhongwenban/js/hooks/extensions/__init__.py
LearningScrapyZhongwenban/js/hooks/extensions/highlight.js
LearningScrapyZhongwenban/js/libs/__init__.py
LearningScrapyZhongwenban/js/libs/jquery.min.js
LearningScrapyZhongwenban/js/libs/localforage.min.js
learning_scrapy_zhongwenban-2024.3.3.0.dist-info/METADATA
learning_scrapy_zhongwenban-2024.3.3.0.dist-info/WHEEL
learning_scrapy_zhongwenban-2024.3.3.0.dist-info/entry_points.txt
learning_scrapy_zhongwenban-2024.3.3.0.dist-info/top_level.txt
learning_scrapy_zhongwenban-2024.3.3.0.dist-info/RECORD
